smacli/__init__.py
smacli/__main__.py
smacli/test.py
smacli/x.py
smacli/data/flash.dat
smacli/jwt/__init__.py
smacom-1.0.2.data/data/data/flash.dat
smacom-1.0.2.dist-info/DESCRIPTION.rst
smacom-1.0.2.dist-info/METADATA
smacom-1.0.2.dist-info/RECORD
smacom-1.0.2.dist-info/WHEEL
smacom-1.0.2.dist-info/entry_points.txt
smacom-1.0.2.dist-info/metadata.json
smacom-1.0.2.dist-info/top_level.txt
