Metadata-Version: 2.0
Name: smacom
Version: 1.0.2
Summary: SamaCOM a Python Package extends main framework functionalities
Home-page: https://github.com/sama-business-services/smacom
Author: ~0x000001
Author-email: io@smasystems.sa
License: UNKNOWN
Project-URL: Bug Reports, https://github.com/sama-business-services/smacom/issues
Project-URL: Funding, https://donate.pypi.org
Project-URL: Say Thanks!, http://saythanks.io/to/sama-business-services
Keywords: smaPython development environment
Platform: UNKNOWN
Classifier: Development Status :: 3 - Alpha
Classifier: Environment :: Console
Classifier: Environment :: Web Environment
Classifier: Operating System :: Microsoft :: Windows
Classifier: Operating System :: MacOS :: MacOS X
Classifier: Operating System :: POSIX :: Linux
Classifier: Topic :: Communications :: Email
Classifier: Topic :: Office/Business
Classifier: Topic :: Software Development :: Bug Tracking
Classifier: License :: OSI Approved :: MIT License
Classifier: Programming Language :: Python :: 3.7
Requires-Python: >=3.6, <4
Provides-Extra: dev
Provides-Extra: test
Requires-Dist: peppercorn
Provides-Extra: dev
Requires-Dist: check-manifest; extra == 'dev'
Provides-Extra: test
Requires-Dist: coverage; extra == 'test'
